specify_cli/__init__.py
specify_cli_mbeacom-0.0.3.dist-info/METADATA
specify_cli_mbeacom-0.0.3.dist-info/WHEEL
specify_cli_mbeacom-0.0.3.dist-info/entry_points.txt
specify_cli_mbeacom-0.0.3.dist-info/licenses/LICENSE
specify_cli_mbeacom-0.0.3.dist-info/RECORD
