Metadata-Version: 2.4
Name: specify-cli-mbeacom
Version: 0.0.3
Summary: Setup tool for Specify spec-driven development projects
License-File: LICENSE
Requires-Python: >=3.11
Requires-Dist: httpx
Requires-Dist: platformdirs
Requires-Dist: readchar
Requires-Dist: rich
Requires-Dist: truststore>=0.10.4
Requires-Dist: typer
